{"id":"ID2798dd20c5dc46a0ac37fd32b2245873","name":"ActionSchema","description":"Action Schema","key":"0155c65a-a7f7-4e91-a0e9-9e7aeb3bead4","inputs":[{"name":"case_id","key":"f257547e-e902-4657-bfdf-ecdbf98f0ed0","required":false,"type":"System.String","jsType":"string","typeNamespace":"system","isList":false,"collectionDataType":null,"customType":null,"properties":[],"version":0},{"name":"in_ElderId","key":"752fc952-13d6-4a70-b1e8-fdd536401b6f","required":false,"customType":null,"properties":[],"version":0,"type":"System.String","typeNamespace":"system","isList":false,"collectionDataType":null},{"name":"out_Source","key":"6859cf4f-61ad-4c09-90ce-10f81130a12a","required":false,"customType":null,"properties":[],"version":0,"type":"System.String","typeNamespace":"system","isList":false,"collectionDataType":null},{"name":"received_at","key":"fbf8ec57-acc9-4f2b-8dd3-16e3abead358","required":false,"customType":null,"properties":[],"version":0,"type":"System.String","typeNamespace":"system","isList":false,"collectionDataType":null},{"name":"in_RawText","key":"c6416453-aa0d-4072-9408-fc52cb51bdf3","required":false,"customType":null,"properties":[],"version":0,"type":"System.String","typeNamespace":"system","isList":false,"collectionDataType":null},{"name":"out_Reason","key":"2ba54792-e42a-4166-8da7-55df9176b3a2","required":false,"customType":null,"properties":[],"version":0,"type":"System.String","typeNamespace":"system","isList":false,"collectionDataType":null},{"name":"fraud_confidence","key":"48217cc5-b2fb-4f9b-804f-7bfe1389b9bc","required":false,"customType":null,"properties":[],"version":0,"type":"System.Decimal","typeNamespace":"system","isList":false,"collectionDataType":null},{"name":"emergency_confidence","key":"d4696ce4-6def-44d4-8521-1e215622be20","required":false,"customType":null,"properties":[],"version":0,"type":"System.Decimal","typeNamespace":"system","isList":false,"collectionDataType":null},{"name":"out_SeverityScore","key":"85f098aa-bc89-43c7-a3e0-2eec10ee1246","required":false,"customType":null,"properties":[],"version":0,"type":"System.Decimal","typeNamespace":"system","isList":false,"collectionDataType":null}],"outputs":[{"name":"reviewer_decision","key":"ed60f759-bc2c-4c3f-a0f3-9a580767a6f5","required":false,"customType":null,"properties":[],"version":0,"type":"System.String","typeNamespace":"system","isList":false,"collectionDataType":null},{"name":"notes","key":"c0992a35-1fab-4caf-8c16-b0af285d0302","required":false,"customType":null,"properties":[],"version":0,"type":"System.String","typeNamespace":"system","isList":false,"collectionDataType":null}],"inOuts":[],"outcomes":[{"name":"SubmitReviewDecision","key":"7562bc17-5b69-4999-b085-dc417ec6d603","required":false,"customType":null,"properties":[],"version":0,"type":"System.String","typeNamespace":"system","isList":false,"collectionDataType":null}],"version":0}